package/__init__.py
package/logger.py
package/loggeringpy.py
loggeringpy-0.9.1.dist-info/LICENSE
loggeringpy-0.9.1.dist-info/METADATA
loggeringpy-0.9.1.dist-info/WHEEL
loggeringpy-0.9.1.dist-info/top_level.txt
loggeringpy-0.9.1.dist-info/RECORD
