Metadata-Version: 2.1
Name: loggeringpy
Version: 0.9.1
Summary: Module for sumple logging
Home-page: https://github.com/K1AYPVA/loggeringpy
Author: K1ayPVA
Author-email: kegor6137@gmail.com
Project-URL: Documentation, https://github.com/K1AYPVA/loggeringpy/tree/main
Keywords: log logs python
Classifier: License :: OSI Approved :: MIT License
Requires-Python: >=3.10
License-File: LICENSE
Requires-Dist: colorama>=0.4.6
Requires-Dist: dacite>=1.9.2
